nlpaeg/__init__.py
nlpaeg/__main__.py
nlpaeg/common_misspelled_eng_words.json
nlpaeg/error_generator.py
nlpaeg/generator.py
nlpaeg/helper_functions.py
nlpaeg/helper_variables.py
nlpaeg/testing_file.py
nlpaeg/data/nlpaeg_pubmed_data_min.csv
nlpaeg/resources/common_misspelled_eng_words.json
nlpaeg-0.1.1.dist-info/METADATA
nlpaeg-0.1.1.dist-info/WHEEL
nlpaeg-0.1.1.dist-info/entry_points.txt
nlpaeg-0.1.1.dist-info/top_level.txt
nlpaeg-0.1.1.dist-info/RECORD
