Metadata-Version: 2.1
Name: nlpaeg
Version: 0.1.1
Summary: Artificial Error Generation (AEG) for Natural Language Processing
Home-page: https://github.com/praveentn/nlpaeg
Author: Praveen Narayan
Author-email: sigmoidptn@gmail.com
License: MIT
Platform: UNKNOWN
Classifier: License :: OSI Approved :: MIT License
Classifier: Programming Language :: Python :: 3
Classifier: Programming Language :: Python :: 3.8
Requires-Dist: numpy
Requires-Dist: pandas
Requires-Dist: lemminflect
Requires-Dist: tqdm
Requires-Dist: requests
